gogo_utils-1.11.1.dist-info/METADATA
gogo_utils-1.11.1.dist-info/RECORD
gogo_utils-1.11.1.dist-info/WHEEL
gogo_utils-1.11.1.dist-info/top_level.txt
gogoutils/__init__.py
gogoutils/formats.py
gogoutils/generator.py
gogoutils/parser.py
