Metadata-Version: 2.1
Name: gogo-utils
Version: 1.11.1
Summary: A utility library that generates service name convention details based on a repo url.
Home-page: https://github.com/foremast/gogo-utils
Author: Sijis Aviles
Author-email: saviles@gogoair.com
License: Apache License (2.0)
Download-URL: https://github.com/foremast/gogo-utils
Keywords: gogo python
Platform: OS Independent
Classifier: Development Status :: 5 - Production/Stable
Classifier: Intended Audience :: Developers
Classifier: Programming Language :: Python :: 2.7
Classifier: Programming Language :: Python :: 3.4
Classifier: Programming Language :: Python :: 3.5
Classifier: Programming Language :: Python :: 3.6
Classifier: License :: OSI Approved :: Apache Software License
Classifier: Operating System :: OS Independent
